cli_support/__init__.py
cli_support/CLI.py
cli_support/cli_assessment_summary.py
cli_support/cli_copyright.py
cli_support/cli_export_restriction.py
cli_support/cli_external_id.py
cli_support/cli_file_item_base.py
cli_support/cli_general_information.py
cli_support/cli_irrelevant_files.py
cli_support/cli_license.py
cli_support/cli_obligation.py
cli_support/license_tools.py
cli_support/py.typed
cli_support/xml_base.py
License.md
cli_support-2.0.2.dist-info/License.md
cli_support-2.0.2.dist-info/METADATA
cli_support-2.0.2.dist-info/WHEEL
cli_support-2.0.2.dist-info/RECORD
