Metadata-Version: 2.1
Name: cli-support
Version: 2.0.2
Summary: Support component license information (CLI) files
Home-page: https://github.com/sw360/clipython
License: MIT
Author: Thomas Graf
Author-email: thomas.graf@siemens.com
Requires-Python: >=3.8,<4.0
Classifier: Development Status :: 5 - Production/Stable
Classifier: Intended Audience :: Developers
Classifier: License :: OSI Approved :: MIT License
Classifier: Natural Language :: English
Classifier: Operating System :: OS Independent
Classifier: Programming Language :: Python :: 3
Classifier: Programming Language :: Python :: 3.8
Classifier: Programming Language :: Python :: 3.9
Classifier: Programming Language :: Python :: 3.10
Classifier: Programming Language :: Python :: 3.11
Classifier: Programming Language :: Python :: 3 :: Only
Project-URL: Repository, https://github.com/sw360/clipython
